{
  "$schema": "https://developer.microsoft.com/json-schemas/fabric/item/report/definition/page/2.0.0/schema.json",
  "name": "456614725719e2bd07a4",
  "displayName": "Sales Bakehouse",
  "displayOption": "FitToPage",
  "height": 720,
  "width": 1280,
  "pageBinding": {
    "name": "c3e6baa5c27e653a8d20",
    "type": "Default",
    "parameters": []
  },
  "objects": {
    "background": [
      {
        "properties": {
          "image": {
            "image": {
              "name": {
                "expr": {
                  "Literal": {
                    "Value": "'SalesDashboardBackground.png'"
                  }
                }
              },
              "url": {
                "expr": {
                  "ResourcePackageItem": {
                    "PackageName": "RegisteredResources",
                    "PackageType": 1,
                    "ItemName": "SalesDashboardBackground6681034248848252.png"
                  }
                }
              },
              "scaling": {
                "expr": {
                  "Literal": {
                    "Value": "'Normal'"
                  }
                }
              }
            }
          },
          "transparency": {
            "expr": {
              "Literal": {
                "Value": "0D"
              }
            }
          }
        }
      }
    ]
  }
}